{
	"cstrike":
	{
		"ActivateMouse":
		{
			"Comment": "0x10216D80 static CSS IDA address June 3 2016",
			"Module": "engine.dll",
			"Pattern": "83 3D ?? ?? ?? ?? ?? 74 4F 8B 0D ?? ?? ?? ?? 8B 01 8B 40 40 FF D0 84 C0 75 0B 8B 0D ?? ?? ?? ?? 8B 01 FF 60 3C"
		},
		"AppActivate":
		{
			"Comment": "0x102013C0 static CSS IDA address June 3 2016",
			"Module": "engine.dll",
			"Pattern": "55 8B EC 8B 45 08 83 78 08 00 0F 95 C0 0F B6 C0 89 45 08 5D E9 ?? ?? ?? ??"
		},
		"MaterialSystem_MaterialsPtr":
		{
			"Comment": "0x101FFFAF static CSS IDA address May 29 2017",
			"Module": "engine.dll",
			"Pattern": "8B 0D ?? ?? ?? ?? 56 8B 11 FF 92 ?? ?? ?? ?? 8B F0 85 F6 74 07 8B 06 8B CE FF 50 08 8B 45 08 89 45 EC 8B 45 0C 53 FF 75 1C",
			"Offset": 2
		},
		"MaterialSystem_GetBackBufferDimensions":
		{
			"Comment": "Static CSS IMaterialSystem vtable offset June 4 2017",
			"VTPtrName": "MaterialSystem_MaterialsPtr",
			"VTIndex": 31
		},
		"D3D9_Device":
		{
			"Comment": "0x100CDDC0 static CSS IDA address May 31 2017",
			"Module": "shaderapidx9.dll",
			"Pattern": "A1 ?? ?? ?? ?? 53 56 8B D9 83 78 30 00 74 0E 68 ?? ?? ?? ?? FF 15 ?? ?? ?? ?? 83 C4 04 8B 8B ?? ?? ?? ?? 8D B3 ?? ?? ?? ?? 85 C9 74 0C 8B 01",
			"Offset": 58
		},
		"DrawLoading":
		{
			"Comment": "0x10105EA0 static CSS IDA address April 22 2017",
			"Module": "engine.dll",
			"Pattern": "80 3D ?? ?? ?? ?? ?? 0F 85 ?? ?? ?? ?? E8 ?? ?? ?? ?? 6A 00 8B C8 8B 10 FF 92 ?? ?? ?? ?? 6A 00 E8 ?? ?? ?? ?? 6A 01 C6 05 ?? ?? ?? ?? ?? E8 ?? ?? ?? ?? 6A 01 E8 ?? ?? ?? ?? 8B 0D ?? ?? ?? ??",
			"Offset": 2
		},
		"View_Render":
		{
			"Comment": "0x100D5EA0 static CSS IDA address May 22 2017",
			"Module": "client.dll",
			"Pattern": "55 8B EC 8B 55 08 83 7A 08 00 74 17 83 7A 0C 00 74 11 8B 0D ?? ?? ?? ?? 52 8B 01 FF 50 14 E8 ?? ?? ?? ?? 5D C2 04 00"
		},
		"StartMovie":
		{
			"Comment": "0x100BF270 static CSS IDA address April 26 2017",
			"Module": "engine.dll",
			"Pattern": "FF 50 44 50 53 56 E8 ?? ?? ?? ?? 68 ?? ?? ?? ?? FF 15 ?? ?? ?? ?? 83 C4 20 5F 5B 5E 8B E5 5D C3",
			"Offset": 6,
			"IsRelativeJump": true
		},
		"StartMovieCommand":
		{
			"Comment": "0x100BEF40 static CSS IDA address April 7 2017",
			"Module": "engine.dll",
			"Pattern": "55 8B EC 83 EC 08 83 3D ?? ?? ?? ?? ?? 0F 85 ?? ?? ?? ?? 8B 4D 08 56 8B 01 83 F8 02 7D 6B 8B 35 ?? ?? ?? ?? 68 ?? ?? ?? ?? FF D6 68 ?? ?? ?? ??"
		},
		"EndMovie":
		{
			"Comment": "0x100BAE40 static CSS IDA address May 22 2016",
			"Module": "engine.dll",
			"Pattern": "80 3D ?? ?? ?? ?? ?? 0F 84 ?? ?? ?? ?? D9 05 ?? ?? ?? ?? 51 B9 ?? ?? ?? ?? D9 1C 24 E8 ?? ?? ?? ?? C7 05 ?? ?? ?? ?? ?? ?? ?? ?? E8 ?? ?? ?? ?? 8B 0D ?? ?? ?? ?? 85 C9 74 38"
		},
		"EndMovieCommand":
		{
			"Comment": "0x100BE970 static CSS IDA address June 29 2017",
			"Module": "engine.dll",
			"Pattern": "80 3D ?? ?? ?? ?? ?? 75 0F 68 ?? ?? ?? ?? FF 15 ?? ?? ?? ?? 83 C4 04 C3 E8 ?? ?? ?? ?? 68 ?? ?? ?? ?? FF 15 ?? ?? ?? ?? 59 C3"
		},
		"SUpdateGuts":
		{
			"Comment": "0x1006E1B7 static CSS IDA address July 4 2017",
			"Module": "engine.dll",
			"Pattern": "E8 ?? ?? ?? ?? 83 C4 04 83 7D C8 00 7C 27 8B 55 C0 85 D2 74 20 A1 ?? ?? ?? ?? 52 8B 08 8B 01 FF 50 14 33 D2 85 D2 74 0D A1 ?? ?? ?? ?? 52 8B 08 8B 01 FF 50 14 8B E5 5D C3",
			"IsRelativeJump": true
		},
		"CvarPtr":
		{
			"Comment": "0x10253CC9 static CSS IDA address August 8 2017",
			"Module": "engine.dll",
			"Pattern": "A3 ?? ?? ?? ?? A3 ?? ?? ?? ?? 83 3D ?? ?? ?? ?? ?? 75 19 8B 04 B7 6A 00 68 ?? ?? ?? ?? FF D0 A3 ?? ?? ?? ?? 83 C4 08 A1 ?? ?? ?? ?? 46 3B F3 7C BD 5F 5E 5B 5D C3",
			"Offset": 1
		},
		"Cvar_FindVar":
		{
			"Comment": "Static CSS ICVar vtable offset August 8 2017",
			"VTPtrName": "CvarPtr",
			"VTIndex": 13
		},
		"IConVar_VTable":
		{
			"Comment": "0x10249A40 + 0xF + 3 static CSS IDA address August 9 2017",
			"Module": "engine.dll",
			"Pattern": "55 8B EC 56 8B F1 8B 46 24 C7 06 ?? ?? ?? ?? C7 46 ?? ?? ?? ?? ?? 85 C0 74 10 50 E8 ?? ?? ?? ?? 83 C4 04 C7 46 ?? ?? ?? ?? ?? F6 45 08 01 C7 06 ?? ?? ?? ?? 74 09 56 E8 ?? ?? ?? ?? 83 C4 04 8B C6 5E 5D C2 04 00",
			"Offset": 18
		},
		"ConCommandBase_VTable":
		{
			"Comment": "0x10249A40 + 0x2E + 2 static CSS IDA address August 9 2017",
			"Module": "engine.dll",
			"Pattern": "55 8B EC 56 8B F1 8B 46 24 C7 06 ?? ?? ?? ?? C7 46 ?? ?? ?? ?? ?? 85 C0 74 10 50 E8 ?? ?? ?? ?? 83 C4 04 C7 46 ?? ?? ?? ?? ?? F6 45 08 01 C7 06 ?? ?? ?? ?? 74 09 56 E8 ?? ?? ?? ?? 83 C4 04 8B C6 5E 5D C2 04 00",
			"Offset": 48
		},
		"Convar_Info":
		{
			"Comment": "4096 (1 << 12) in iconvar.h August 8 2017",
			"NeverAsStringFlag": 4096,
			"Variant": 0
		},
		"ConVar_Create":
		{
			"Comment": "0x1024A110 static CSS IDA address August 9 2017",
			"Module": "engine.dll",
			"Pattern": "55 8B EC 8B 45 0C 85 C0 56 57 BF ?? ?? ?? ?? 8B F1 8B D7 0F 45 D0 89 76 1C 89 56 20 8D 4A 01 90 8A 02 42 84 C0 75 F9 2B D1 8D 42 01 50 89 46 28 E8 ?? ?? ?? ??"
		},
		"ConCommandBase_Info":
		{
			"Comment": "Static CSS ConCommandBase vtable offset August 9 2017",
			"Variant": 0
		},
		"ConCommandBase_CreateBase":
		{
			"Comment": "Static CSS ConCommandBase vtable offset August 9 2017",
			"VTPtrName": "ConCommandBase_VTable",
			"VTIndex": 8
		},
		"CCommand_Info":
		{
			"Variant": 0
		},
		"ConCommand_Info":
		{
			"Variant": 0
		}
	},

	"hl2":
	{
		"Inherit": "cstrike"
	},

	"tf":
	{
		"Inherit": "cstrike"
	},
	
	"momentum":
	{
		"Inherit": "cstrike"
	}
}
